keycard/__init__.py
keycard/apdu.py
keycard/card_interface.py
keycard/constants.py
keycard/exceptions.py
keycard/keycard.py
keycard/preconditions.py
keycard/secure_channel.py
keycard/transport.py
keycard/commands/__init__.py
keycard/commands/change_secret.py
keycard/commands/derive_key.py
keycard/commands/export_key.py
keycard/commands/factory_reset.py
keycard/commands/generate_key.py
keycard/commands/generate_menmonic.py
keycard/commands/get_data.py
keycard/commands/get_status.py
keycard/commands/ident.py
keycard/commands/init.py
keycard/commands/load_key.py
keycard/commands/mutually_authenticate.py
keycard/commands/open_secure_channel.py
keycard/commands/pair.py
keycard/commands/remove_key.py
keycard/commands/select.py
keycard/commands/set_pinless_path.py
keycard/commands/sign.py
keycard/commands/store_data.py
keycard/commands/unblock_pin.py
keycard/commands/unpair.py
keycard/commands/verify_pin.py
keycard/crypto/__init__.py
keycard/crypto/aes.py
keycard/crypto/generate_pairing_token.py
keycard/crypto/padding.py
keycard/parsing/__init__.py
keycard/parsing/application_info.py
keycard/parsing/capabilities.py
keycard/parsing/exported_key.py
keycard/parsing/identity.py
keycard/parsing/keypath.py
keycard/parsing/signature_result.py
keycard/parsing/tlv.py
keycard-0.3.0.dist-info/licenses/LICENSE
keycard-0.3.0.dist-info/WHEEL
keycard-0.3.0.dist-info/METADATA
keycard-0.3.0.dist-info/RECORD
