Metadata-Version: 2.4
Name: keycard
Version: 0.3.0
Summary: KeyCard Python SDK - APDU communication and cryptographic utilities.
Author-email: mmlado <developer@mmlado.com>
License-Expression: MIT
License-File: LICENSE
Requires-Dist: pyscard
Requires-Dist: ecdsa
Requires-Dist: pyaes
Requires-Dist: pytest ; extra == "dev"
Requires-Dist: pytest-cov ; extra == "dev"
Requires-Dist: coverage ; extra == "dev"
Requires-Dist: sphinx ; extra == "dev"
Requires-Dist: sphinx-autodoc-typehints ; extra == "dev"
Requires-Dist: flake8 ; extra == "dev"
Requires-Dist: mypy ; extra == "dev"
Requires-Dist: mnemonic ; extra == "dev"
Project-URL: Documentation, https://mmlado.github.io/keycard-py/
Project-URL: Homepage, https://github.com/mmlado/keycard-py
Provides-Extra: dev
